{"version": 0.6, "generator": "Overpass API 0.7.62.8 e802775f", "osm3s": {"timestamp_osm_base": "2025-10-20T00:17:37Z", "copyright": "The data included in this document is from www.openstreetmap.org. The data is made available under ODbL."}, "elements": [{"type": "node", "id": 2674119124, "lat": 46.4705741, "lon": -90.1246432}, {"type": "node", "id": 2688966504, "lat": 46.5243356, "lon": -90.0629721}, {"type": "node", "id": 2949519722, "lat": 46.4636921, "lon": -90.1190771}, {"type": "node", "id": 2949519723, "lat": 46.4637069, "lon": -90.1247661}, {"type": "node", "id": 2949519737, "lat": 46.4674096, "lon": -90.1146681}, {"type": "node", "id": 2949519757, "lat": 46.4705449, "lon": -90.1135982}, {"type": "node", "id": 2964776077, "lat": 46.5243005, "lon": -90.0711808}, {"type": "node", "id": 2964776079, "lat": 46.525536, "lon": -90.0711297}, {"type": "node", "id": 2964776080, "lat": 46.5259342, "lon": -90.0731468}, {"type": "node", "id": 2964776081, "lat": 46.5264729, "lon": -90.0645593}, {"type": "node", "id": 2964776082, "lat": 46.5265315, "lon": -90.0629848}, {"type": "node", "id": 2964776083, "lat": 46.5277905, "lon": -90.0645338}, {"type": "node", "id": 2964776084, "lat": 46.5278783, "lon": -90.0731638}, {"type": "way", "id": 291486114, "nodes": [2674119124, 2949519723, 2949519722, 2949519737, 2949519757, 2674119124], "tags": {"addr:city": "Ironwood", "addr:housenumber": "200", "addr:postcode": "49938", "addr:state": "MI", "addr:street": "Country Club Road", "gnis:feature_id": "1623368", "leisure": "golf_course", "name": "Gogebic Country Club", "phone": "+1-906-932-2515", "website": "https://www.gogebiccountryclub.com/"}}, {"type": "way", "id": 292927531, "nodes": [2688966504, 2964776077, 2964776079, 2964776080, 2964776084, 2964776083, 2964776081, 2964776082, 2688966504], "tags": {"addr:city": "Bessemer", "addr:housenumber": "N11868", "addr:postcode": "49911", "addr:state": "MI", "addr:street": "Heron Lane", "gnis:feature_id": "2127535", "leisure": "golf_course", "name": "Boulder Creek Golf Course", "phone": "+1-906-932-9066", "website": "http://www.bouldercreekgolfmi.com/"}}]}